<annotation>
	<folder>ImageSets</folder>
	<filename>96.jpg</filename>
	<path>/Users/Eugene/Desktop/FoodCounter/mmdetection_object_detection_demo/data/VOCdevkit/VOC2007/ImageSets/96.jpg</path>
	<source>
		<database>Unknown</database>
	</source>
	<size>
		<width>800</width>
		<height>600</height>
		<depth>3</depth>
	</size>
	<segmented>0</segmented>
	<object>
		<name>Customer</name>
		<pose>Unspecified</pose>
		<truncated>0</truncated>
		<difficult>0</difficult>
		<bndbox>
			<xmin>431</xmin>
			<ymin>181</ymin>
			<xmax>546</xmax>
			<ymax>269</ymax>
		</bndbox>
	</object>
	<object>
		<name>Employee3</name>
		<pose>Unspecified</pose>
		<truncated>0</truncated>
		<difficult>0</difficult>
		<bndbox>
			<xmin>402</xmin>
			<ymin>193</ymin>
			<xmax>567</xmax>
			<ymax>580</ymax>
		</bndbox>
	</object>
</annotation>
